ywit_event_countdown/__init__.py
ywit_event_countdown/cli.py
ywit_event_countdown/countdown.py
ywit_event_countdown-2020.11.1.dist-info/entry_points.txt
ywit_event_countdown-2020.11.1.dist-info/LICENSE
ywit_event_countdown-2020.11.1.dist-info/WHEEL
ywit_event_countdown-2020.11.1.dist-info/METADATA
ywit_event_countdown-2020.11.1.dist-info/RECORD
