Metadata-Version: 2.1
Name: ywit-event-countdown
Version: 2020.11.1
Summary: This library and application will tell you how long until NetAp's next YWIT event
Home-page: https://github.com/NetApp-YWIT/ywit_2020_ci_cd_workshop
License: MIT
Author: NetApp
Author-email: ng-ywit-questions@netapp.com
Requires-Python: >=3.7
Classifier: License :: OSI Approved :: MIT License
Classifier: Programming Language :: Python :: 3
Classifier: Programming Language :: Python :: 3.7
Classifier: Programming Language :: Python :: 3.8
Classifier: Programming Language :: Python :: 3.9
Requires-Dist: requests (>=2.25.0,<3.0.0)
Project-URL: Documentation, https://netapp-ywit.github.io/ywit_2020_ci_cd_workshop
Project-URL: Repository, https://github.com/NetApp-YWIT/ywit_2020_ci_cd_workshop
